fastapi_project_gen/__init__.py
fastapi_project_gen/generator.py
fastapi_create_project-1.0.2.dist-info/LICENSE
fastapi_create_project-1.0.2.dist-info/METADATA
fastapi_create_project-1.0.2.dist-info/WHEEL
fastapi_create_project-1.0.2.dist-info/entry_points.txt
fastapi_create_project-1.0.2.dist-info/top_level.txt
fastapi_create_project-1.0.2.dist-info/RECORD
