Metadata-Version: 2.1
Name: fastapi-create-project
Version: 1.0.2
Summary: A tool to generate FastAPI project structures
Home-page: UNKNOWN
Author: Your Name
License: UNKNOWN
Platform: UNKNOWN
License-File: LICENSE
